 {
  "1": {
    "name": "3 Sonderbonbons"
    },
  "2": {
    "name": "5 silberne Sananabeeren"
    },
  "3": {
    "name": "Bidiza/Voltobal"
    },
  "4": {
    "name": "Bisasam/Glumanda/Schiggy"
    },
  "5": {
    "name": "Evoli/Sonnkern"
    },
  "6": {
    "name": "Machollo/Menki"
    },
  "7": {
    "name": "Owei/Snubbull"
    },
  "8": {
    "name": "Quapsel/Vulpix"
    },
  "9": {
    "name": "Aerodactyl"  
    },
  "10": {
    "name": "Amonitas"  
    },
  "11": {
    "name": "Anorith"  
    },
  "12": {
    "name": "Bidiza"  
    },
  "13": {
    "name": "Bisasam"  
    },
  "14": {
    "name": "Chaneira"
    },
  "15": {
    "name": "Dratini"
    },
  "16": {
    "name": "Elektek"
    },
  "17": {
    "name": "Evoli"
    },
  "18": {
    "name": "Fukano"  
    },
  "19": {
    "name": "Glumanda"
    },
  "20": {
    "name": "Hunduster"  
    },
  "21": {
    "name": "Kabuto"  
    },
  "22": {
    "name": "Karpador"
    },
  "23": {
    "name": "Lapras"  
    },
  "24": {
    "name": "Larvitar"
    },
  "25": {
    "name": "Machollo"
    },
  "26": {
    "name": "Magmar"
    },
  "27": {
    "name": "Magnetilo"
    },
  "28": {
    "name": "Menki"  
    },
  "29": {
    "name": "Nebulak"
    },
  "30": {
    "name": "Onix"
    },
  "31": {
    "name": "Owei"
    },
  "32": {
    "name": "Pandir"
    },
  "33": {
    "name": "Quapsel"
    },
  "34": {
    "name": "Rossana"
    },
  "35": {
    "name": "Sandan"  
    },
  "36": {
    "name": "Schiggy"
    },
  "37": {
    "name": "Snubbull"  
    },
  "38": {
    "name": "Sonnkern"  
    },
  "39": {
    "name": "Starmie"  
    },
  "40": {
    "name": "Tentoxa"  
    },
  "41": {
    "name": "Tragosso"
    },
  "42": {
    "name": "Traumato"  
    },
  "43": {
    "name": "Voltenso"  
    },
  "44": {
    "name": "Voltobal"
    },
  "45": {
    "name": "Vulpix"
    }
}
